image_gen/__init__.py
image_gen/server.py
mseep_image_gen-0.1.4.dist-info/licenses/LICENSE
mseep_image_gen-0.1.4.dist-info/METADATA
mseep_image_gen-0.1.4.dist-info/WHEEL
mseep_image_gen-0.1.4.dist-info/entry_points.txt
mseep_image_gen-0.1.4.dist-info/top_level.txt
mseep_image_gen-0.1.4.dist-info/RECORD
